dnry/srvhost/builder/__init__.py
dnry/srvhost/builder/hosting_environment.py
dnry/srvhost/builder/noop_host.py
dnry/srvhost/builder/srv_host_base.py
dnry/srvhost/builder/srv_host_builder.py
dnry/srvhost/builder/srv_host_context.py
dnry/srvhost/builder/types.py
dnry_srvhost_builder-0.2.0.dist-info/LICENSE
dnry_srvhost_builder-0.2.0.dist-info/METADATA
dnry_srvhost_builder-0.2.0.dist-info/WHEEL
dnry_srvhost_builder-0.2.0.dist-info/top_level.txt
dnry_srvhost_builder-0.2.0.dist-info/RECORD
