Metadata-Version: 2.1
Name: dnry-srvhost-builder
Version: 0.2.0
Summary: Builder for a service host.
Home-page: https://github.com/en0/dnry-srvhost-builder
Author: Ian Laird
Author-email: irlaird@gmail.com
License: MIT
Keywords: srvhost,dnry
Platform: UNKNOWN
Classifier: Programming Language :: Python :: 3
Classifier: License :: OSI Approved :: MIT License
Classifier: Operating System :: OS Independent
Requires-Dist: dnry-config (==0.1.4)
Requires-Dist: pyioc3 (==1.3.0)
